windadjustment/PointAdjustment.py
windadjustment/RegionAdjustment.py
windadjustment/WindSpeedVisualizer.py
windadjustment/__init__.py
windadjustment-1.0.0.dist-info/licenses/LICENSE
windadjustment-1.0.0.dist-info/METADATA
windadjustment-1.0.0.dist-info/WHEEL
windadjustment-1.0.0.dist-info/top_level.txt
windadjustment-1.0.0.dist-info/RECORD
